{"id":"931408cc-efa6-4dae-915d-a17aa7a0e6f0","title":"National Championship","status":"closed","coverage":"full","scheduled":"2015-04-07T01:18:00+00:00","attendance":71149,"lead_changes":16,"times_tied":5,"clock":"00:00","half":2,"home":{"name":"Blue Devils","market":"Duke","id":"faeb1160-5d15-4f26-99fc-c441cf21fc7f","points":68,"rank":4,"scoring":[{"number":1,"sequence":1,"points":31,"type":"half"},{"number":2,"sequence":2,"points":37,"type":"half"}],"leaders":{"points":[{"full_name":"Tyus Jones","position":"G","primary_position":"NA","jersey_number":"5","id":"ed06b9be-0d73-4e37-9064-f1556a1797a0","statistics":{"minutes":"37:00","field_goals_made":7,"field_goals_att":13,"field_goals_pct":53.8,"three_points_made":2,"three_points_att":3,"three_points_pct":66.7,"two_points_made":5,"two_points_att":10,"two_points_pct":0.5,"blocked_att":1,"free_throws_made":7,"free_throws_att":7,"free_throws_pct":100.0,"offensive_rebounds":0,"defensive_rebounds":5,"rebounds":5,"assists":1,"turnovers":1,"steals":0,"blocks":0,"assists_turnover_ratio":1.0,"personal_fouls":1,"tech_fouls":0,"flagrant_fouls":0,"points":23}}],"rebounds":[{"full_name":"Justise Winslow","position":"F","primary_position":"NA","jersey_number":"12","id":"576da23f-8c2f-4e27-a760-a80eaf86ff0b","statistics":{"minutes":"32:00","field_goals_made":3,"field_goals_att":9,"field_goals_pct":33.3,"three_points_made":1,"three_points_att":2,"three_points_pct":50.0,"two_points_made":2,"two_points_att":7,"two_points_pct":0.286,"blocked_att":0,"free_throws_made":4,"free_throws_att":7,"free_throws_pct":57.1,"offensive_rebounds":0,"defensive_rebounds":9,"rebounds":9,"assists":1,"turnovers":2,"steals":1,"blocks":3,"assists_turnover_ratio":0.5,"personal_fouls":4,"tech_fouls":0,"flagrant_fouls":0,"points":11}}],"assists":[{"full_name":"Amile Jefferson","position":"F","primary_position":"NA","jersey_number":"21","id":"61af49d8-936e-4577-b2fa-e291f41bbae3","statistics":{"minutes":"21:00","field_goals_made":1,"field_goals_att":1,"field_goals_pct":100.0,"three_points_made":0,"three_points_att":0,"three_points_pct":0.0,"two_points_made":1,"two_points_att":1,"two_points_pct":1.0,"blocked_att":0,"free_throws_made":0,"free_throws_att":0,"free_throws_pct":0.0,"offensive_rebounds":1,"defensive_rebounds":6,"rebounds":7,"assists":2,"turnovers":0,"steals":1,"blocks":3,"assists_turnover_ratio":0,"personal_fouls":3,"tech_fouls":0,"flagrant_fouls":0,"points":2}}]}},"away":{"name":"Badgers","market":"Wisconsin","id":"c7569eae-5b93-4197-b204-6f3a62146b25","points":63,"rank":3,"scoring":[{"number":1,"sequence":1,"points":31,"type":"half"},{"number":2,"sequence":2,"points":32,"type":"half"}],"leaders":{"points":[{"full_name":"Frank Kaminsky","position":"F","primary_position":"NA","jersey_number":"44","id":"ed2f8d67-3593-4b26-a242-a92bc114d740","statistics":{"minutes":"39:00","field_goals_made":7,"field_goals_att":16,"field_goals_pct":43.8,"three_points_made":2,"three_points_att":4,"three_points_pct":50.0,"two_points_made":5,"two_points_att":12,"two_points_pct":0.417,"blocked_att":0,"free_throws_made":5,"free_throws_att":6,"free_throws_pct":83.3,"offensive_rebounds":1,"defensive_rebounds":11,"rebounds":12,"assists":2,"turnovers":2,"steals":1,"blocks":1,"assists_turnover_ratio":1.0,"personal_fouls":1,"tech_fouls":0,"flagrant_fouls":0,"points":21}}],"rebounds":[{"full_name":"Frank Kaminsky","position":"F","primary_position":"NA","jersey_number":"44","id":"ed2f8d67-3593-4b26-a242-a92bc114d740","statistics":{"minutes":"39:00","field_goals_made":7,"field_goals_att":16,"field_goals_pct":43.8,"three_points_made":2,"three_points_att":4,"three_points_pct":50.0,"two_points_made":5,"two_points_att":12,"two_points_pct":0.417,"blocked_att":0,"free_throws_made":5,"free_throws_att":6,"free_throws_pct":83.3,"offensive_rebounds":1,"defensive_rebounds":11,"rebounds":12,"assists":2,"turnovers":2,"steals":1,"blocks":1,"assists_turnover_ratio":1.0,"personal_fouls":1,"tech_fouls":0,"flagrant_fouls":0,"points":21}}],"assists":[{"full_name":"Bronson Koenig","position":"G","primary_position":"NA","jersey_number":"24","id":"6344815c-ac3a-4506-827f-de05ec5e37c9","statistics":{"minutes":"31:00","field_goals_made":4,"field_goals_att":9,"field_goals_pct":44.4,"three_points_made":1,"three_points_att":3,"three_points_pct":33.3,"two_points_made":3,"two_points_att":6,"two_points_pct":0.5,"blocked_att":0,"free_throws_made":1,"free_throws_att":2,"free_throws_pct":50.0,"offensive_rebounds":0,"defensive_rebounds":0,"rebounds":0,"assists":4,"turnovers":0,"steals":0,"blocks":0,"assists_turnover_ratio":0,"personal_fouls":3,"tech_fouls":0,"flagrant_fouls":0,"points":10}}]}}}